seq/decode.v
module decode(dstE,dstM,srcA,srcB,icode,rA,rB,cnd);
input [3:0] icode;
input [3:0] rA;
input [3:0] rB;
input cnd;

output [3:0] dstE;
output [3:0] dstM;
output [3:0] srcA;
output [3:0] srcB;

parameter IHALT = 4'h0;
parameter INOP = 4'h1;
parameter IRRMOVQ = 4'h2;
parameter IIRMOVQ = 4'h3;
parameter IRMMOVQ = 4'h4;
parameter IMRMOVQ = 4'h5;
parameter IOPQ = 4'h6;
parameter IJXX = 4'h7;
parameter ICALL = 4'h8;
parameter IRET = 4'h9;
parameter IPUSHQ = 4'ha;
parameter IPOPQ = 4'hb;

assign srcA = icode == IRRMOVQ ? rA: icode == IOPQ ? rA: icode == IPUSHQ ? rA: icode == IRET ? 4'h4: icode == IRRMOVQ ? rA: icode == IPOPQ ? 4'h4 : 4'hf; 

assign srcB = icode == IMRMOVQ ? rB: icode == IOPQ ? rB: icode == IRMMOVQ ? rB: icode == IRET ? 4'h4: icode == ICALL ? 4'h4: icode == IPUSHQ ? 4'h4: icode == IPOPQ ? 4'h4 : 4'hf;

assign dstE =  icode == IRRMOVQ ? (cnd ? rB : 4'hf): icode == IIRMOVQ ? rB: icode == IOPQ ? rB: icode == IRET ? 4'h4: icode == ICALL ? 4'h4: icode == IPUSHQ ? 4'h4: icode == IPOPQ ? 4'h4 : 4'hf; 

assign dstM = icode == IMRMOVQ ? rA: icode == IPOPQ ? rA: 4'hf; 

endmodule

seq/decode_tb.v
module decode_tb();

reg [3:0] icode;
reg [3:0] rA;
reg [3:0] rB; 
reg cnd;
output [3:0] srcA;
output [3:0] srcB;
output [3:0] dstE;
output [3:0] dstM;

decode decode(
    .dstE(dstE),
    .dstM(dstM),
    .srcA(srcA),
    .srcB(srcB),
    .icode(icode),
    .rA(rA),
    .rB(rB),
    .cnd(cnd)


  );

initial begin 
    $dumpfile("decode.vcd");
    $dumpvars(0,decode_tb);

    cnd=1'b0;

    icode = 4'b0010; rA = 4'b0010; rB = 4'b0010;
    #10 cnd = ~cnd; 
    #10 cnd = ~cnd;
    icode = 4'b0011; rA = 4'b0000; rB = 4'b1000;
    #10 cnd = ~cnd; 
    #10 cnd = ~cnd;
    icode = 4'b0100; rA = 4'b1100; rB = 4'b0101;
    #10 cnd = ~cnd; 
    #10 cnd = ~cnd;
    icode = 4'b0101; rA = 4'b1110; rB = 4'b1001;
    #10 cnd = ~cnd; 
    #10 cnd = ~cnd;
    icode = 4'b0110; rA = 4'b0011; rB = 4'b0001;
    #10 cnd = ~cnd; 
    #10 cnd = ~cnd;
    icode = 4'b1000; rA = 4'b0000; rB = 4'b1110;
    #10 cnd = ~cnd; 
    #10 cnd = ~cnd;
    icode = 4'b1001; rA = 4'b0100; rB = 4'b1001;
    #10 cnd = ~cnd; 
    #10 cnd = ~cnd;
    icode = 4'b1010; rA = 4'b0101; rB = 4'b1101;
    #10 cnd = ~cnd; 
    #10 cnd = ~cnd;
    icode = 4'b1011; rA = 4'b0000; rB = 4'b0000;
    #10 cnd = ~cnd; 
    #10 cnd = ~cnd;

end 
  
initial 
    $monitor("cnd = %d icode = %b rA = %b rB = %b srcA = %g srcB = %g\n",cnd,icode,rA,rB,srcA,srcB);
endmodule

seq/decode.vcd
$date
	Thu Mar 10 06:05:51 2022
$end
$version
	Icarus Verilog
$end
$timescale
	1s
$end
$scope module decode_tb $end
$var wire 4 ! srcB [3:0] $end
$var wire 4 " srcA [3:0] $end
$var wire 4 # dstM [3:0] $end
$var wire 4 $ dstE [3:0] $end
$var reg 1 % cnd $end
$var reg 4 & icode [3:0] $end
$var reg 4 ' rA [3:0] $end
$var reg 4 ( rB [3:0] $end
$scope module decode $end
$var wire 1 % cnd $end
$var wire 4 ) icode [3:0] $end
$var wire 4 * rA [3:0] $end
$var wire 4 + rB [3:0] $end
$var wire 4 , srcB [3:0] $end
$var wire 4 - srcA [3:0] $end
$var wire 4 . dstM [3:0] $end
$var wire 4 / dstE [3:0] $end
$upscope $end
$upscope $end
$enddefinitions $end
#0
$dumpvars
b1111 /
b1111 .
b10 -
b1111 ,
b10 +
b10 *
b10 )
b10 (
b10 '
b10 &
0%
b1111 $
b1111 #
b10 "
b1111 !
$end
#10
b10 $
b10 /
1%
#20
b1111 "
b1111 -
b1000 $
b1000 /
b1000 (
b1000 +
b0 '
b0 *
b11 &
b11 )
0%
#30
1%
#40
b101 !
b101 ,
b1111 $
b1111 /
b101 (
b101 +
b1100 '
b1100 *
b100 &
b100 )
0%
#50
1%
#60
b1001 !
b1001 ,
b1110 #
b1110 .
b1001 (
b1001 +
b1110 '
b1110 *
b101 &
b101 )
0%
#70
1%
#80
b1 $
b1 /
b11 "
b11 -
b1 !
b1 ,
b1111 #
b1111 .
b1 (
b1 +
b11 '
b11 *
b110 &
b110 )
0%
#90
1%
#100
b100 $
b100 /
b1111 "
b1111 -
b100 !
b100 ,
b1110 (
b1110 +
b0 '
b0 *
b1000 &
b1000 )
0%
#110
1%
#120
b100 "
b100 -
b1001 (
b1001 +
b100 '
b100 *
b1001 &
b1001 )
0%
#130
1%
#140
b100 !
b100 ,
b100 $
b100 /
b101 "
b101 -
b1101 (
b1101 +
b101 '
b101 *
b1010 &
b1010 )
0%
#150
1%
#160
b100 "
b100 -
b0 #
b0 .
b0 (
b0 +
b0 '
b0 *
b1011 &
b1011 )
0%
#170
1%
#180
0%
